{
  "project_info": {
    "project_number": "794652876294",
    "firebase_url": "https://book-grab-9c5c9.firebaseio.com",
    "project_id": "book-grab-9c5c9",
    "storage_bucket": "book-grab-9c5c9.appspot.com"
  },
  "client": [
    {
      "client_info": {
        "mobilesdk_app_id": "1:794652876294:android:446c4109157f0047f1ed87",
        "android_client_info": {
          "package_name": "com.a3cheezepizza.book_grab"
        }
      },
      "oauth_client": [
        {
          "client_id": "794652876294-bsold3qcj5nl1a3uob45e92n03eb9621.apps.googleusercontent.com",
          "client_type": 3
        }
      ],
      "api_key": [
        {
          "current_key": "AIzaSyAFAHTP6kGtu2ab6ZxU_azegcwcYMZu3SA"
        }
      ],
      "services": {
        "appinvite_service": {
          "other_platform_oauth_client": [
            {
              "client_id": "794652876294-bsold3qcj5nl1a3uob45e92n03eb9621.apps.googleusercontent.com",
              "client_type": 3
            }
          ]
        }
      }
    },
    {
      "client_info": {
        "mobilesdk_app_id": "1:794652876294:android:a0626c684d607e4ff1ed87",
        "android_client_info": {
          "package_name": "com.bookgrab.firebase_login"
        }
      },
      "oauth_client": [
        {
          "client_id": "794652876294-bsold3qcj5nl1a3uob45e92n03eb9621.apps.googleusercontent.com",
          "client_type": 3
        }
      ],
      "api_key": [
        {
          "current_key": "AIzaSyAFAHTP6kGtu2ab6ZxU_azegcwcYMZu3SA"
        }
      ],
      "services": {
        "appinvite_service": {
          "other_platform_oauth_client": [
            {
              "client_id": "794652876294-bsold3qcj5nl1a3uob45e92n03eb9621.apps.googleusercontent.com",
              "client_type": 3
            }
          ]
        }
      }
    }
  ],
  "configuration_version": "1"
}